.clang-format
.flake8
.gitignore
.gitmodules
CHANGELOG.md
CODEOWNERS
CODE_OF_CONDUCT
Dockerfile
Dockerfile-cuda
Dockerfile-embedded
LICENSE
MANIFEST.in
Makefile
README.md
__init__.py
description.txt
packages.txt
setup.py
./src/opendr/__init__.py
./src/opendr/_setup.py
./src/opendr/_version.py
./src/opendr/control/__init__.py
./src/opendr/engine/__init__.py
./src/opendr/engine/constants.py
./src/opendr/engine/data.py
./src/opendr/engine/datasets.py
./src/opendr/engine/example_learner.py
./src/opendr/engine/learners.py
./src/opendr/engine/target.py
./src/opendr/perception/__init__.py
./src/opendr/perception/facial_expression_recognition/__init__.py
./src/opendr/perception/facial_expression_recognition/image_based_facial_emotion_estimation/README.md
./src/opendr/perception/facial_expression_recognition/image_based_facial_emotion_estimation/__init__.py
./src/opendr/perception/facial_expression_recognition/image_based_facial_emotion_estimation/dependencies.ini
./src/opendr/perception/facial_expression_recognition/image_based_facial_emotion_estimation/facial_emotion_learner.py
./src/opendr/perception/facial_expression_recognition/image_based_facial_emotion_estimation/algorithm/__init__.py
./src/opendr/perception/facial_expression_recognition/image_based_facial_emotion_estimation/algorithm/model/__init__.py
./src/opendr/perception/facial_expression_recognition/image_based_facial_emotion_estimation/algorithm/model/cbam.py
./src/opendr/perception/facial_expression_recognition/image_based_facial_emotion_estimation/algorithm/model/diversified_esr.py
./src/opendr/perception/facial_expression_recognition/image_based_facial_emotion_estimation/algorithm/model/esr_9.py
./src/opendr/perception/facial_expression_recognition/image_based_facial_emotion_estimation/algorithm/utils/__init__.py
./src/opendr/perception/facial_expression_recognition/image_based_facial_emotion_estimation/algorithm/utils/datasets.py
./src/opendr_toolkit_facial_expression_recognition.egg-info/PKG-INFO
./src/opendr_toolkit_facial_expression_recognition.egg-info/SOURCES.txt
./src/opendr_toolkit_facial_expression_recognition.egg-info/dependency_links.txt
./src/opendr_toolkit_facial_expression_recognition.egg-info/requires.txt
./src/opendr_toolkit_facial_expression_recognition.egg-info/top_level.txt
